converter/__init__.py
converter_jamiesear-0.0.1.dist-info/LICENSE
converter_jamiesear-0.0.1.dist-info/METADATA
converter_jamiesear-0.0.1.dist-info/WHEEL
converter_jamiesear-0.0.1.dist-info/top_level.txt
converter_jamiesear-0.0.1.dist-info/RECORD
