Metadata-Version: 2.1
Name: converter-jamiesear
Version: 0.0.1
Summary: Unit converter using metres and centermetres
Home-page: https://github.com/JamieSear/unit_converter
Author: Jamie Sear
License: UNKNOWN
Platform: UNKNOWN
Classifier: Programming Language :: Python :: 3
Classifier: License :: Free For Home Use
Classifier: Operating System :: OS Independent
